{
  "format": "LINXO_CONNECT_DIRECT_ACCOUNT_API_V3",
  "connections": [
    {
      "accounts": [
        {
          "transactions": [
            {
              "transaction_amount": {
                "currency": "EUR",
                "amount": "-80"
              },
              "booking_date": "2023-04-13T23:00:00.000Z",
              "remittance_information": [
                "CB RETRAIT"
              ],
              "id": "54yaVJRZjE8kNVv"
            },
            {
              "transaction_amount": {
                "currency": "EUR",
                "amount": "400"
              },
              "booking_date": "2023-04-13T23:00:00.000Z",
              "remittance_information": [
                "VIREMENT EN VOTRE FAVEUR CAF"
              ],
              "id": "thWl9UFp1pDvZJy"
            },
            {
              "transaction_amount": {
                "currency": "EUR",
                "amount": "400"
              },
              "booking_date": "2023-04-17T23:00:00.000Z",
              "remittance_information": [
                "VIREMENT LOYER PAR MR XXXX"
              ],
              "id": "JwSrK4CEFlzXvR9"
            },
            {
              "transaction_amount": {
                "currency": "EUR",
                "amount": "-45"
              },
              "booking_date": "2023-04-17T23:00:00.000Z",
              "remittance_information": [
                "CB RETRAIT"
              ],
              "id": "ogfczN6lkNMuJU0"
            },
            {
              "transaction_amount": {
                "currency": "EUR",
                "amount": "-45.93"
              },
              "booking_date": "2023-04-18T23:00:00.000Z",
              "remittance_information": [
                "PAIEMENT PAR CARTE CARREFOUR"
              ],
              "id": "GZuNPdmt57GV0Sa"
            },
            {
              "transaction_amount": {
                "currency": "EUR",
                "amount": "-30.32"
              },
              "booking_date": "2023-04-18T23:00:00.000Z",
              "remittance_information": [
                "ACHAT CB UBER EATS EUR 30,32 CARTE NO XXX"
              ],
              "id": "kaIW0WtIVmDY6VC"
            },
            {
              "transaction_amount": {
                "currency": "EUR",
                "amount": "-160"
              },
              "booking_date": "2023-04-18T23:00:00.000Z",
              "remittance_information": [
                "ACHAT CB AMAZON"
              ],
              "id": "fLfUMJ6G0wNROwH"
            },
            {
              "transaction_amount": {
                "currency": "EUR",
                "amount": "-45.4"
              },
              "booking_date": "2023-04-18T23:00:00.000Z",
              "remittance_information": [
                "ACHAT CB DOBELL XXXX CARTE NUMERO XXX"
              ],
              "id": "9jB1yGpVwGsrqe6"
            },
            {
              "transaction_amount": {
                "currency": "EUR",
                "amount": "-39.99"
              },
              "booking_date": "2023-04-18T23:00:00.000Z",
              "remittance_information": [
                "PRELEVEMENT DE Orange REF"
              ],
              "id": "mCywweDbGWB96hU"
            },
            {
              "transaction_amount": {
                "currency": "EUR",
                "amount": "-600"
              },
              "booking_date": "2023-04-18T23:00:00.000Z",
              "remittance_information": [
                "PRET IMMOBILIER ECH XXXXXX"
              ],
              "id": "Xtl8TaGyavILnzC"
            },
            {
              "transaction_amount": {
                "currency": "EUR",
                "amount": "-60"
              },
              "booking_date": "2023-04-19T23:00:00.000Z",
              "remittance_information": [
                "Prélèvement de Eca Assurances"
              ],
              "id": "LRxRYvITEeYYHlV"
            },
            {
              "transaction_amount": {
                "currency": "EUR",
                "amount": "-200"
              },
              "booking_date": "2023-04-21T23:00:00.000Z",
              "remittance_information": [
                "VIREMENT MR XXX"
              ],
              "id": "B9cyAJ08sjW4Ekp"
            },
            {
              "transaction_amount": {
                "currency": "EUR",
                "amount": "-130"
              },
              "booking_date": "2023-04-22T23:00:00.000Z",
              "remittance_information": [
                "PRELEVEMENT DE ACTIVE ASSURANCES REF"
              ],
              "id": "Yeg1tAXTqsdIkb8"
            },
            {
              "transaction_amount": {
                "currency": "EUR",
                "amount": "-19.99"
              },
              "booking_date": "2023-04-23T23:00:00.000Z",
              "remittance_information": [
                "PRLV SEPA ORANGE MOBILE"
              ],
              "id": "Ch18cgNIxE4GIOk"
            },
            {
              "transaction_amount": {
                "currency": "EUR",
                "amount": "-150.65"
              },
              "booking_date": "2023-04-23T23:00:00.000Z",
              "remittance_information": [
                "ACHAT CB ZARA XXXX CARTE NUMERO XXX"
              ],
              "id": "TP9UN6cvDfCoa3H"
            },
            {
              "transaction_amount": {
                "currency": "EUR",
                "amount": "-75.24"
              },
              "booking_date": "2023-04-27T23:00:00.000Z",
              "remittance_information": [
                "ACHAT CB PHARMACIE PARIS XX"
              ],
              "id": "gYhRZ0iG1YeFnt5"
            },
            {
              "transaction_amount": {
                "currency": "EUR",
                "amount": "-24.2"
              },
              "booking_date": "2023-04-28T23:00:00.000Z",
              "remittance_information": [
                "PRLV SEPA EDF CLIENTS PAR MDT XXXX"
              ],
              "id": "KFvznJ978Bmx5Am"
            },
            {
              "transaction_amount": {
                "currency": "EUR",
                "amount": "-44.3"
              },
              "booking_date": "2023-04-30T23:00:00.000Z",
              "remittance_information": [
                "PRELEVEMENT DE ACTIVE ASSURANCES"
              ],
              "id": "pkjWyZOBDKf02xL"
            },
            {
              "transaction_amount": {
                "currency": "EUR",
                "amount": "-71.46"
              },
              "booking_date": "2023-05-01T23:00:00.000Z",
              "remittance_information": [
                "ACHAT CB"
              ],
              "id": "aCFpggZqvpKp9Fw"
            },
            {
              "transaction_amount": {
                "currency": "EUR",
                "amount": "-78.89"
              },
              "booking_date": "2023-05-02T23:00:00.000Z",
              "remittance_information": [
                "CARTE CB AUCHAN"
              ],
              "id": "mLi0lml1X18ZxbY"
            },
            {
              "transaction_amount": {
                "currency": "EUR",
                "amount": "-34"
              },
              "booking_date": "2023-05-03T23:00:00.000Z",
              "remittance_information": [
                "ACHAT CB"
              ],
              "id": "1ryNByZI53LOFDj"
            },
            {
              "transaction_amount": {
                "currency": "EUR",
                "amount": "-33.46"
              },
              "booking_date": "2023-05-03T23:00:00.000Z",
              "remittance_information": [
                "ACHAT CB FROG"
              ],
              "id": "tqhEQdv79QNNk88"
            },
            {
              "transaction_amount": {
                "currency": "EUR",
                "amount": "1300"
              },
              "booking_date": "2023-05-03T23:00:00.000Z",
              "remittance_information": [
                "ASSURANCE RETRAITE CNAV"
              ],
              "id": "R1pOzTfrW1lnc34"
            },
            {
              "transaction_amount": {
                "currency": "EUR",
                "amount": "-39.27"
              },
              "booking_date": "2023-05-04T23:00:00.000Z",
              "remittance_information": [
                "ACHAT CB"
              ],
              "id": "X8CGQSKrnF9gbK1"
            },
            {
              "transaction_amount": {
                "currency": "EUR",
                "amount": "-42.17"
              },
              "booking_date": "2023-05-04T23:00:00.000Z",
              "remittance_information": [
                "PAIEMENT PAR CARTE CARREFOUR"
              ],
              "id": "h5zWIiNtRFiDQQI"
            },
            {
              "transaction_amount": {
                "currency": "EUR",
                "amount": "-16.4"
              },
              "booking_date": "2023-05-05T23:00:00.000Z",
              "remittance_information": [
                "ACHAT CB"
              ],
              "id": "i8DfFY8iXvn1d3E"
            },
            {
              "transaction_amount": {
                "currency": "EUR",
                "amount": "-100"
              },
              "booking_date": "2023-05-12T23:00:00.000Z",
              "remittance_information": [
                "CB RETRAIT"
              ],
              "id": "7LfqF8OVLg4GETC"
            },
            {
              "transaction_amount": {
                "currency": "EUR",
                "amount": "400"
              },
              "booking_date": "2023-05-14T23:00:00.000Z",
              "remittance_information": [
                "VIREMENT EN VOTRE FAVEUR CAF"
              ],
              "id": "zhD74sMi92OaUX3"
            },
            {
              "transaction_amount": {
                "currency": "EUR",
                "amount": "400"
              },
              "booking_date": "2023-05-14T23:00:00.000Z",
              "remittance_information": [
                "VIREMENT LOYER PAR MR XXXX"
              ],
              "id": "Oz40942NpVFIuCD"
            },
            {
              "transaction_amount": {
                "currency": "EUR",
                "amount": "-45"
              },
              "booking_date": "2023-05-16T23:00:00.000Z",
              "remittance_information": [
                "CB RETRAIT"
              ],
              "id": "yKxXCzExlfYBVZd"
            },
            {
              "transaction_amount": {
                "currency": "EUR",
                "amount": "-35.93"
              },
              "booking_date": "2023-05-16T23:00:00.000Z",
              "remittance_information": [
                "PAIEMENT PAR CARTE CARREFOUR"
              ],
              "id": "wTyvBma24EIgf1X"
            },
            {
              "transaction_amount": {
                "currency": "EUR",
                "amount": "-28.32"
              },
              "booking_date": "2023-05-16T23:00:00.000Z",
              "remittance_information": [
                "ACHAT CB UBER EATS EUR 28,32 CARTE NO XXX"
              ],
              "id": "zUk91P4jYmpcL25"
            },
            {
              "transaction_amount": {
                "currency": "EUR",
                "amount": "-160"
              },
              "booking_date": "2023-05-17T23:00:00.000Z",
              "remittance_information": [
                "ACHAT CB AMAZON"
              ],
              "id": "U3w9u5HbbA89lNB"
            },
            {
              "transaction_amount": {
                "currency": "EUR",
                "amount": "-45.4"
              },
              "booking_date": "2023-05-17T23:00:00.000Z",
              "remittance_information": [
                "ACHAT CB DOBELL XXXX CARTE NUMERO XXX"
              ],
              "id": "htVQ1236SPDiZA4"
            },
            {
              "transaction_amount": {
                "currency": "EUR",
                "amount": "-39.99"
              },
              "booking_date": "2023-05-19T23:00:00.000Z",
              "remittance_information": [
                "PRELEVEMENT DE Orange REF"
              ],
              "id": "pIuyZBgHMToUf6O"
            },
            {
              "transaction_amount": {
                "currency": "EUR",
                "amount": "-600"
              },
              "booking_date": "2023-05-19T23:00:00.000Z",
              "remittance_information": [
                "PRET IMMOBILIER ECH XXXXXX"
              ],
              "id": "qU2wWzpKsEpeIrB"
            },
            {
              "transaction_amount": {
                "currency": "EUR",
                "amount": "-200"
              },
              "booking_date": "2023-05-19T23:00:00.000Z",
              "remittance_information": [
                "VIREMENT MR XXX"
              ],
              "id": "vqJqyShi7GWP7Wx"
            },
            {
              "transaction_amount": {
                "currency": "EUR",
                "amount": "-130"
              },
              "booking_date": "2023-05-20T23:00:00.000Z",
              "remittance_information": [
                "PRELEVEMENT DE ACTIVE ASSURANCES REF"
              ],
              "id": "GmEqhCaPlfCQpEs"
            },
            {
              "transaction_amount": {
                "currency": "EUR",
                "amount": "-60"
              },
              "booking_date": "2023-05-20T23:00:00.000Z",
              "remittance_information": [
                "Prélèvement de Eca Assurances"
              ],
              "id": "eBjEymxhcmoFpm7"
            },
            {
              "transaction_amount": {
                "currency": "EUR",
                "amount": "-19.99"
              },
              "booking_date": "2023-05-23T23:00:00.000Z",
              "remittance_information": [
                "PRLV SEPA ORANGE MOBILE"
              ],
              "id": "fh48qCfg2eoJpvP"
            },
            {
              "transaction_amount": {
                "currency": "EUR",
                "amount": "-50.65"
              },
              "booking_date": "2023-05-24T23:00:00.000Z",
              "remittance_information": [
                "ACHAT CB ZARA XXXX CARTE NUMERO XXX"
              ],
              "id": "rwW5vf2p24SwDHV"
            },
            {
              "transaction_amount": {
                "currency": "EUR",
                "amount": "-15.24"
              },
              "booking_date": "2023-05-26T23:00:00.000Z",
              "remittance_information": [
                "ACHAT CB PHARMACIE PARIS XX"
              ],
              "id": "HbrsIgLYFT6nKaZ"
            },
            {
              "transaction_amount": {
                "currency": "EUR",
                "amount": "-44.3"
              },
              "booking_date": "2023-05-28T23:00:00.000Z",
              "remittance_information": [
                "PRELEVEMENT DE ACTIVE ASSURANCES"
              ],
              "id": "0RYxLYD27nHCJ1z"
            },
            {
              "transaction_amount": {
                "currency": "EUR",
                "amount": "-24.2"
              },
              "booking_date": "2023-05-29T23:00:00.000Z",
              "remittance_information": [
                "PRLV SEPA EDF CLIENTS PAR MDT XXXX"
              ],
              "id": "bCyIHa1OefOCAWP"
            },
            {
              "transaction_amount": {
                "currency": "EUR",
                "amount": "-91.46"
              },
              "booking_date": "2023-05-31T23:00:00.000Z",
              "remittance_information": [
                "ACHAT CB"
              ],
              "id": "JioHj3RkU6B13xz"
            },
            {
              "transaction_amount": {
                "currency": "EUR",
                "amount": "-78.89"
              },
              "booking_date": "2023-06-01T23:00:00.000Z",
              "remittance_information": [
                "CARTE CB AUCHAN"
              ],
              "id": "N7CLkpWXTFcfT7s"
            },
            {
              "transaction_amount": {
                "currency": "EUR",
                "amount": "-56"
              },
              "booking_date": "2023-06-02T23:00:00.000Z",
              "remittance_information": [
                "ACHAT CB"
              ],
              "id": "7KVPEQ5ABV3bwjS"
            },
            {
              "transaction_amount": {
                "currency": "EUR",
                "amount": "-83.46"
              },
              "booking_date": "2023-06-03T23:00:00.000Z",
              "remittance_information": [
                "ACHAT CB JULES"
              ],
              "id": "xzzJC2a6ogp1fpU"
            },
            {
              "transaction_amount": {
                "currency": "EUR",
                "amount": "1300"
              },
              "booking_date": "2023-06-03T23:00:00.000Z",
              "remittance_information": [
                "ASSURANCE RETRAITE CNAV"
              ],
              "id": "Kz1bU5l4T1E0UCA"
            },
            {
              "transaction_amount": {
                "currency": "EUR",
                "amount": "-56.27"
              },
              "booking_date": "2023-06-03T23:00:00.000Z",
              "remittance_information": [
                "ACHAT CB"
              ],
              "id": "EDfl1HEfsarCl0h"
            },
            {
              "transaction_amount": {
                "currency": "EUR",
                "amount": "-32.17"
              },
              "booking_date": "2023-06-04T23:00:00.000Z",
              "remittance_information": [
                "PAIEMENT PAR CARTE CARREFOUR"
              ],
              "id": "d1H5XclFunJjHj7"
            },
            {
              "transaction_amount": {
                "currency": "EUR",
                "amount": "-200"
              },
              "booking_date": "2023-06-04T23:00:00.000Z",
              "remittance_information": [
                "CB RETRAIT"
              ],
              "id": "yQKwXoE22gRIHDj"
            },
            {
              "transaction_amount": {
                "currency": "EUR",
                "amount": "-56"
              },
              "booking_date": "2023-06-05T23:00:00.000Z",
              "remittance_information": [
                "ACHAT CB UBER EATS EUR 56 CARTE NO XXX"
              ],
              "id": "gA2wL0P8YcOuXT5"
            },
            {
              "transaction_amount": {
                "currency": "EUR",
                "amount": "400"
              },
              "booking_date": "2023-06-11T23:00:00.000Z",
              "remittance_information": [
                "VIREMENT EN VOTRE FAVEUR CAF"
              ],
              "id": "lVcpFYt3EBxcT3X"
            },
            {
              "transaction_amount": {
                "currency": "EUR",
                "amount": "400"
              },
              "booking_date": "2023-06-14T23:00:00.000Z",
              "remittance_information": [
                "VIREMENT LOYER PAR MR XXXX"
              ],
              "id": "BfiJMoJnjpXtDUs"
            },
            {
              "transaction_amount": {
                "currency": "EUR",
                "amount": "-45"
              },
              "booking_date": "2023-06-14T23:00:00.000Z",
              "remittance_information": [
                "CB RETRAIT"
              ],
              "id": "nBgqG53HGUjDJ29"
            },
            {
              "transaction_amount": {
                "currency": "EUR",
                "amount": "-60.54"
              },
              "booking_date": "2023-06-16T23:00:00.000Z",
              "remittance_information": [
                "PAIEMENT PAR CARTE CARREFOUR"
              ],
              "id": "PsJ0pGA0XhnAZfh"
            },
            {
              "transaction_amount": {
                "currency": "EUR",
                "amount": "-18.32"
              },
              "booking_date": "2023-06-16T23:00:00.000Z",
              "remittance_information": [
                "ACHAT CB UBER EATS EUR 28,32 CARTE NO XXX"
              ],
              "id": "wSVsK90hFIcIT3S"
            },
            {
              "transaction_amount": {
                "currency": "EUR",
                "amount": "-80"
              },
              "booking_date": "2023-06-16T23:00:00.000Z",
              "remittance_information": [
                "ACHAT CB AMAZON"
              ],
              "id": "fVue58kmdFlEBnN"
            },
            {
              "transaction_amount": {
                "currency": "EUR",
                "amount": "-32.4"
              },
              "booking_date": "2023-06-17T23:00:00.000Z",
              "remittance_information": [
                "ACHAT CB DOBELL XXXX CARTE NUMERO XXX"
              ],
              "id": "6HllU0kwGWmneHW"
            },
            {
              "transaction_amount": {
                "currency": "EUR",
                "amount": "-39.99"
              },
              "booking_date": "2023-06-17T23:00:00.000Z",
              "remittance_information": [
                "PRELEVEMENT DE Orange REF"
              ],
              "id": "DFVG1QCQn6qyGDM"
            },
            {
              "transaction_amount": {
                "currency": "EUR",
                "amount": "-600"
              },
              "booking_date": "2023-06-19T23:00:00.000Z",
              "remittance_information": [
                "PRET IMMOBILIER ECH XXXXXX"
              ],
              "id": "6aPTQ3zHwRENB97"
            },
            {
              "transaction_amount": {
                "currency": "EUR",
                "amount": "-200"
              },
              "booking_date": "2023-06-19T23:00:00.000Z",
              "remittance_information": [
                "VIREMENT MR XXX"
              ],
              "id": "GHOglObKWVwMrGt"
            },
            {
              "transaction_amount": {
                "currency": "EUR",
                "amount": "-130"
              },
              "booking_date": "2023-06-19T23:00:00.000Z",
              "remittance_information": [
                "PRELEVEMENT DE ACTIVE ASSURANCES REF"
              ],
              "id": "lLLdVURMlaFTQAO"
            },
            {
              "transaction_amount": {
                "currency": "EUR",
                "amount": "-60"
              },
              "booking_date": "2023-06-20T23:00:00.000Z",
              "remittance_information": [
                "Prélèvement de Eca Assurances"
              ],
              "id": "wg422HvuCwS9Qx2"
            },
            {
              "transaction_amount": {
                "currency": "EUR",
                "amount": "-19.99"
              },
              "booking_date": "2023-06-23T23:00:00.000Z",
              "remittance_information": [
                "PRLV SEPA ORANGE MOBILE"
              ],
              "id": "8jijHA5cbr4czed"
            },
            {
              "transaction_amount": {
                "currency": "EUR",
                "amount": "-60.65"
              },
              "booking_date": "2023-06-24T23:00:00.000Z",
              "remittance_information": [
                "ACHAT CB PRIMARK XXXX CARTE NUMERO XXX"
              ],
              "id": "Mg86BwmYSYq2oBn"
            },
            {
              "transaction_amount": {
                "currency": "EUR",
                "amount": "-35.24"
              },
              "booking_date": "2023-06-26T23:00:00.000Z",
              "remittance_information": [
                "ACHAT CB PHARMACIE PARIS XX"
              ],
              "id": "b4qfdlxZA8Rkyt4"
            },
            {
              "transaction_amount": {
                "currency": "EUR",
                "amount": "-24.2"
              },
              "booking_date": "2023-06-26T23:00:00.000Z",
              "remittance_information": [
                "PRLV SEPA EDF CLIENTS PAR MDT XXXX"
              ],
              "id": "wwmtUQJIE8zxCNU"
            },
            {
              "transaction_amount": {
                "currency": "EUR",
                "amount": "-44.3"
              },
              "booking_date": "2023-06-28T23:00:00.000Z",
              "remittance_information": [
                "PRELEVEMENT DE ACTIVE ASSURANCES"
              ],
              "id": "wDxalNGY8lcNpwe"
            },
            {
              "transaction_amount": {
                "currency": "EUR",
                "amount": "-81.46"
              },
              "booking_date": "2023-07-01T23:00:00.000Z",
              "remittance_information": [
                "ACHAT CB"
              ],
              "id": "AL6ijGiLpQ2uyyz"
            },
            {
              "transaction_amount": {
                "currency": "EUR",
                "amount": "-58.89"
              },
              "booking_date": "2023-07-02T23:00:00.000Z",
              "remittance_information": [
                "CARTE CB AUCHAN"
              ],
              "id": "EYvlRjv9S7riYK3"
            },
            {
              "transaction_amount": {
                "currency": "EUR",
                "amount": "-50"
              },
              "booking_date": "2023-07-03T23:00:00.000Z",
              "remittance_information": [
                "CB RETRAIT"
              ],
              "id": "ZbrHZD2i1TGYsa3"
            },
            {
              "transaction_amount": {
                "currency": "EUR",
                "amount": "-39.46"
              },
              "booking_date": "2023-07-04T23:00:00.000Z",
              "remittance_information": [
                "ACHAT CB"
              ],
              "id": "YrsyGWYxQNefKcV"
            },
            {
              "transaction_amount": {
                "currency": "EUR",
                "amount": "1300"
              },
              "booking_date": "2023-07-04T23:00:00.000Z",
              "remittance_information": [
                "ASSURANCE RETRAITE CNAV"
              ],
              "id": "ghZq3IXBpqHP1d6"
            },
            {
              "transaction_amount": {
                "currency": "EUR",
                "amount": "-39.27"
              },
              "booking_date": "2023-07-05T23:00:00.000Z",
              "remittance_information": [
                "ACHAT CB"
              ],
              "id": "6wxCaOrjRP2bNp2"
            },
            {
              "transaction_amount": {
                "currency": "EUR",
                "amount": "-42.17"
              },
              "booking_date": "2023-07-05T23:00:00.000Z",
              "remittance_information": [
                "PAIEMENT PAR CARTE CARREFOUR"
              ],
              "id": "1logGgDT7h6A8xX"
            },
            {
              "transaction_amount": {
                "currency": "EUR",
                "amount": "-16.4"
              },
              "booking_date": "2023-07-10T22:00:00.000Z",
              "remittance_information": [
                "ACHAT CB"
              ],
              "id": "mHUXS3hP4BtJgfe"
            }
          ],
          "name": "Compte Courant 01",
          "balances": [
            {
              "balance_amount": {
                "currency": "EUR",
                "amount": "1014.38"
              },
              "reference_date": "2023-07-10T22:00:00.000Z"
            }
          ],
          "currency": "EUR",
          "type": "CASH_ACCOUNT",
          "usage": "PRIVATE",
          "account_id": "KooDgo1cWY5WG51"
        }
      ]
    }
  ]
}